typenv/__init__.py
typenv/py.typed
typenv-0.2.0.dist-info/LICENSE
typenv-0.2.0.dist-info/WHEEL
typenv-0.2.0.dist-info/METADATA
typenv-0.2.0.dist-info/RECORD
