Metadata-Version: 2.1
Name: typenv
Version: 0.2.0
Summary: Typed environment variable parsing for Python
Home-page: https://github.com/hukkinj1/typenv
License: MIT
Keywords: environment,variables,typed,configuration
Author: hukkinj1
Author-email: hukkinj1@users.noreply.github.com
Requires-Python: >=3.7,<4.0
Classifier: Intended Audience :: Developers
Classifier: License :: OSI Approved :: MIT License
Classifier: Natural Language :: English
Classifier: Programming Language :: Python :: 3
Classifier: Programming Language :: Python :: 3.7
Classifier: Programming Language :: Python :: 3.8
Classifier: Programming Language :: Python :: 3.9
Classifier: Topic :: Software Development :: Libraries :: Python Modules
Classifier: Typing :: Typed
Requires-Dist: python-dotenv (>=0.10.3)
Requires-Dist: typing-extensions (>=3.7.4,<4.0.0); python_version < "3.8"
Project-URL: Changelog, https://github.com/hukkinj1/typenv/blob/master/CHANGELOG.md
Project-URL: Repository, https://github.com/hukkinj1/typenv
